{
  "meta": {
    "generated_at": "2026-05-16T15:12:00.958Z",
    "limit_requested": 50,
    "rows_received": 50,
    "source": "invoices table, soft-deleted excluded, order created_at DESC",
    "stats": {
      "total": 50,
      "with_file_hash": 50,
      "with_supplier_id": 11,
      "with_project_id": 9,
      "with_supplier_nif": 29,
      "direction_emitida": 10,
      "direction_recibida": 40,
      "doc_types": {
        "factura": 28,
        "otro": 21,
        "rectificativa": 1
      }
    }
  },
  "snapshot": [
    {
      "id": "12eafc39-1184-400a-bb01-0d29eb5ef3ef",
      "number": null,
      "file_hash": "e2d3242592cdf20d94ee93b5a8b7f510369be2ff63cb27abd3876a3e2575fff4",
      "email_message_id": "19e2d767957666c9",
      "original_filename": "Factura 0057.pdf",
      "direction": "recibida",
      "doc_type": "otro",
      "review_status": "pendiente",
      "payment_status": "pendiente",
      "supplier_id": null,
      "supplier_nif": null,
      "supplier_name": null,
      "project_id": null,
      "project_code": null,
      "project_name": null,
      "issue_date": null,
      "amount_total": null,
      "created_at": "2026-05-16T01:05:50.55739+00:00"
    },
    {
      "id": "ab984467-aa44-4cdb-b52c-bd4b33f4ed75",
      "number": null,
      "file_hash": "3ada1f2276970f071dce1f48217f999c6f138dc8f5f6c376218681f29c534783",
      "email_message_id": "test-postfix-1778883451-7d0852",
      "original_filename": "test-factura-strcmp-7d0852.pdf",
      "direction": "recibida",
      "doc_type": "otro",
      "review_status": "pendiente",
      "payment_status": "pendiente",
      "supplier_id": null,
      "supplier_nif": null,
      "supplier_name": null,
      "project_id": null,
      "project_code": null,
      "project_name": null,
      "issue_date": null,
      "amount_total": null,
      "created_at": "2026-05-15T22:18:36.293524+00:00"
    },
    {
      "id": "be63c7c0-0363-464f-b79f-62862d3f31bc",
      "number": null,
      "file_hash": "1ff563feade4dc30db3fdb95193f63e0c4c742a4e94bd8d6350f9e4859ad3539",
      "email_message_id": "test-postfix-1778883196-63371d",
      "original_filename": "test-factura-strcmp-63371d.pdf",
      "direction": "recibida",
      "doc_type": "otro",
      "review_status": "pendiente",
      "payment_status": "pendiente",
      "supplier_id": null,
      "supplier_nif": null,
      "supplier_name": null,
      "project_id": null,
      "project_code": null,
      "project_name": null,
      "issue_date": null,
      "amount_total": null,
      "created_at": "2026-05-15T22:14:21.062528+00:00"
    },
    {
      "id": "94e2cac8-16c0-4325-ac51-116c5bd5d6df",
      "number": null,
      "file_hash": "bdc4a3403c1b75e201bb6d5ed83a654e52ae0dae9fc2a75d148847fb4b964e98",
      "email_message_id": "test-postfix-1778882687-0ae70d",
      "original_filename": "test-factura-strcmp-0ae70d.pdf",
      "direction": "recibida",
      "doc_type": "otro",
      "review_status": "pendiente",
      "payment_status": "pendiente",
      "supplier_id": null,
      "supplier_nif": null,
      "supplier_name": null,
      "project_id": null,
      "project_code": null,
      "project_name": null,
      "issue_date": null,
      "amount_total": null,
      "created_at": "2026-05-15T22:05:52.265211+00:00"
    },
    {
      "id": "1fc92e9a-5e89-46c7-8799-b70b6aa52025",
      "number": null,
      "file_hash": "75f93d43c905550548985e1bb6121ab54c75c826662e09017bb0b059ba2be758",
      "email_message_id": "test-postfix-1778882391-d3c8fd",
      "original_filename": "test-factura-strcmp-d3c8fd.pdf",
      "direction": "recibida",
      "doc_type": "otro",
      "review_status": "pendiente",
      "payment_status": "pendiente",
      "supplier_id": null,
      "supplier_nif": null,
      "supplier_name": null,
      "project_id": null,
      "project_code": null,
      "project_name": null,
      "issue_date": null,
      "amount_total": null,
      "created_at": "2026-05-15T22:00:55.315626+00:00"
    },
    {
      "id": "24cd2102-76d0-4fa1-88ea-6ade0e8991ce",
      "number": null,
      "file_hash": "5c022ec60150a827695e6bec81b4d293b28c32d67ec6a802728a05bc89609b53",
      "email_message_id": "test-postfix-1778881877",
      "original_filename": "test-factura-postfix.pdf",
      "direction": "recibida",
      "doc_type": "otro",
      "review_status": "pendiente",
      "payment_status": "pendiente",
      "supplier_id": null,
      "supplier_nif": null,
      "supplier_name": null,
      "project_id": null,
      "project_code": null,
      "project_name": null,
      "issue_date": null,
      "amount_total": null,
      "created_at": "2026-05-15T21:52:28.865012+00:00"
    },
    {
      "id": "c39a93d7-3e2c-4339-b71d-4921f3f60b83",
      "number": null,
      "file_hash": "6316159238c0558234743c784133524696e451f8d69a497b43f5346fd6f0b700",
      "email_message_id": "19e2d6ce1d370c04",
      "original_filename": "Factura 0057.pdf",
      "direction": "recibida",
      "doc_type": "otro",
      "review_status": "pendiente",
      "payment_status": "pendiente",
      "supplier_id": null,
      "supplier_nif": null,
      "supplier_name": null,
      "project_id": null,
      "project_code": null,
      "project_name": null,
      "issue_date": null,
      "amount_total": null,
      "created_at": "2026-05-15T21:06:56.993767+00:00"
    },
    {
      "id": "fdd7d66e-7d7a-4f2f-a129-26fab23f9661",
      "number": "A-2026-076950",
      "file_hash": "482d4b74a8015a7a137c0d0918dec85bb339bd2fc5a593931443295117fb4739",
      "email_message_id": "19e286237c1fc391",
      "original_filename": "IMG_3224.jpeg",
      "direction": "recibida",
      "doc_type": "factura",
      "review_status": "pendiente",
      "payment_status": "pendiente",
      "supplier_id": "1503a458-0021-4dc2-9ecd-1fd3a3f0946a",
      "supplier_nif": "B85636579",
      "supplier_name": "Amovens",
      "project_id": null,
      "project_code": null,
      "project_name": null,
      "issue_date": "2026-04-11",
      "amount_total": 136.6,
      "created_at": "2026-05-14T21:51:56.449275+00:00"
    },
    {
      "id": "18c49a5d-795e-43c4-ad4b-da2433a67cae",
      "number": "A-2026-082110",
      "file_hash": "5f6bb51cc8f32b3d4d753a3a6a19e720eda245636bde161f4a000a5e0fe9770e",
      "email_message_id": "19e283db1f4b4a97",
      "original_filename": "IMG_3225.jpeg",
      "direction": "recibida",
      "doc_type": "factura",
      "review_status": "pendiente",
      "payment_status": "pendiente",
      "supplier_id": null,
      "supplier_nif": "B85636579",
      "supplier_name": null,
      "project_id": null,
      "project_code": null,
      "project_name": null,
      "issue_date": "2026-04-17",
      "amount_total": 154.75,
      "created_at": "2026-05-14T20:57:36.42499+00:00"
    },
    {
      "id": "4e50dd4f-e005-4142-9527-a2fedcdefb5a",
      "number": "A-2026-080190",
      "file_hash": "2601a766b90d53ca83ececaf2f2c322744bf4985764c91a1d519c931c89afc27",
      "email_message_id": "19e283520323c528",
      "original_filename": "IMG_3226.jpeg",
      "direction": "recibida",
      "doc_type": "factura",
      "review_status": "pendiente",
      "payment_status": "pendiente",
      "supplier_id": null,
      "supplier_nif": "B85636579",
      "supplier_name": null,
      "project_id": null,
      "project_code": null,
      "project_name": null,
      "issue_date": "2026-04-15",
      "amount_total": 11.6,
      "created_at": "2026-05-14T20:42:21.719059+00:00"
    },
    {
      "id": "f749b6ef-d650-4837-bce5-d0f9aee7cc34",
      "number": "A-2026-104004",
      "file_hash": "e9f278546f2acb40ee3b9bcba7648b73dfdaa65e1772bffeba2e9a1c21f2bdab",
      "email_message_id": "19e1d757f4da0802",
      "original_filename": "1778507968390.jpg",
      "direction": "recibida",
      "doc_type": "factura",
      "review_status": "pendiente",
      "payment_status": "pendiente",
      "supplier_id": null,
      "supplier_nif": "B85636579",
      "supplier_name": null,
      "project_id": null,
      "project_code": null,
      "project_name": null,
      "issue_date": "2026-05-09",
      "amount_total": 43.75,
      "created_at": "2026-05-14T20:01:15.362619+00:00"
    },
    {
      "id": "52b62ec3-873a-4ac4-bcce-b1a3704a1dff",
      "number": "CHI 11-25",
      "file_hash": "9804ef78fd7a6b6faab66e6417bbbf8908c600582ed316a16e7e166735ff3641",
      "email_message_id": "test-final-cliente-1778360329",
      "original_filename": "CHI_011-25_Marich.pdf",
      "direction": "emitida",
      "doc_type": "factura",
      "review_status": "pendiente",
      "payment_status": "pendiente",
      "supplier_id": null,
      "supplier_nif": null,
      "supplier_name": null,
      "project_id": "11dc9a2a-bf59-4356-81d4-a5fd5fe6e9a0",
      "project_code": "OBR-2025-005",
      "project_name": "Collado de Marichiva 5",
      "issue_date": "2025-10-17",
      "amount_total": 4770.92,
      "created_at": "2026-05-09T20:59:07.565963+00:00"
    },
    {
      "id": "c793f5ff-9a1e-4e0c-bf95-44197a0a4746",
      "number": "CHI 02-25",
      "file_hash": "85a7e1e7c3fde2cc9dde93f4bf4ba9b61173c2f377a4ee1026a0d42afc883e5a",
      "email_message_id": "batch7-7-1778359367",
      "original_filename": "1y3Glw-51VqoOu2bAw_qVDsEBdNYJML5P__CHI_02-25_1ª_CERTIFICACION_REFORMA_MAJADAHONDA..pdf",
      "direction": "emitida",
      "doc_type": "factura",
      "review_status": "error",
      "payment_status": "pendiente",
      "supplier_id": null,
      "supplier_nif": null,
      "supplier_name": null,
      "project_id": "f739756c-86f4-472a-9313-1ccb1915f34f",
      "project_code": "OBR-2025-004",
      "project_name": "Majadahonda",
      "issue_date": "2025-03-05",
      "amount_total": 8131.39,
      "created_at": "2026-05-09T20:43:03.005175+00:00"
    },
    {
      "id": "371007a4-48ba-4d59-9b09-afad6aad93df",
      "number": "CHI 08-25",
      "file_hash": "99a1034a2615f8e8e42e7bf76af372fa9cb7e65337a1317770398c865e5cfe95",
      "email_message_id": "batch7-6-1778359273",
      "original_filename": "1utxeBMslldTmrQznruLcP3JlAFo8gqnC__CHI_08-25_COLLADO_MARICHIVA_5.pdf",
      "direction": "emitida",
      "doc_type": "factura",
      "review_status": "pendiente",
      "payment_status": "pendiente",
      "supplier_id": null,
      "supplier_nif": null,
      "supplier_name": null,
      "project_id": "11dc9a2a-bf59-4356-81d4-a5fd5fe6e9a0",
      "project_code": "OBR-2025-005",
      "project_name": "Collado de Marichiva 5",
      "issue_date": "2025-08-22",
      "amount_total": 13358.93,
      "created_at": "2026-05-09T20:41:30.17917+00:00"
    },
    {
      "id": "0e98b27f-9618-46de-8386-3504772238aa",
      "number": "CHI 01-25",
      "file_hash": "b9ca1fb4692029f4c8fa617dc5038a82839e41fa6ec9728301adddc118a897ea",
      "email_message_id": "batch7-5-1778359181",
      "original_filename": "1YmsQRFuf6klhkQGBgJVAUeeZoL9-dxBj__CHI_01-25_PROV_FONDOS_REFORMA_MAJADAHONDA..pdf",
      "direction": "emitida",
      "doc_type": "factura",
      "review_status": "error",
      "payment_status": "pendiente",
      "supplier_id": null,
      "supplier_nif": null,
      "supplier_name": null,
      "project_id": "f739756c-86f4-472a-9313-1ccb1915f34f",
      "project_code": "OBR-2025-004",
      "project_name": "Majadahonda",
      "issue_date": "2025-02-04",
      "amount_total": 13530.52,
      "created_at": "2026-05-09T20:39:56.102377+00:00"
    },
    {
      "id": "4eca9728-53b2-4728-b6df-c4d2ffd98916",
      "number": "CHI 13-25",
      "file_hash": "137c9f68de006a2f7390f7027c42a428d0335aec53f82c0de8fffe2f67fb221c",
      "email_message_id": "batch7-4-1778359088",
      "original_filename": "1TPCKuX41IPlADuqhqKxf4PTM9ltv8vo0__CHI_13-25_MARICHIVA_5.pdf",
      "direction": "emitida",
      "doc_type": "factura",
      "review_status": "pendiente",
      "payment_status": "pendiente",
      "supplier_id": null,
      "supplier_nif": null,
      "supplier_name": null,
      "project_id": "11dc9a2a-bf59-4356-81d4-a5fd5fe6e9a0",
      "project_code": "OBR-2025-005",
      "project_name": "Collado de Marichiva 5",
      "issue_date": "2025-11-04",
      "amount_total": 6305.93,
      "created_at": "2026-05-09T20:38:24.243041+00:00"
    },
    {
      "id": "e8b40c17-a964-44c9-8c46-66455873ab4d",
      "number": "F250038",
      "file_hash": "9fa456cba6409f115d0a02cf1d0266411c1d0829f2b4f2ee8fd8b17eb7586eed",
      "email_message_id": "batch7-3-1778358998",
      "original_filename": "1PNfLxyLkBh7cILCD2JYsMm2lf2eXiVrp__ajc_cousillas_F250038_CATHEDRAL_HOUSE_INVESTMENT_SL.pdf",
      "direction": "recibida",
      "doc_type": "factura",
      "review_status": "error",
      "payment_status": "pendiente",
      "supplier_id": "fea68f88-7d37-45f8-8428-53497dc53a2d",
      "supplier_nif": "B72946395",
      "supplier_name": "ACJ Cousillas S.L.",
      "project_id": null,
      "project_code": null,
      "project_name": null,
      "issue_date": "2025-02-25",
      "amount_total": 7260,
      "created_at": "2026-05-09T20:36:52.128264+00:00"
    },
    {
      "id": "21595459-8e52-4f0b-9271-cceb8c6eb8c0",
      "number": "CHI 10-25",
      "file_hash": "c08c96c71f3681906c54465a34100feaeede6a739cced7939a88d1234c234098",
      "email_message_id": "batch7-2-1778358900",
      "original_filename": "1IdBEsQZ1rS2MFrcmEaV5FAV9f6xAXYg0__CHI_010-24_MArich.pdf",
      "direction": "emitida",
      "doc_type": "factura",
      "review_status": "pendiente",
      "payment_status": "pendiente",
      "supplier_id": null,
      "supplier_nif": null,
      "supplier_name": null,
      "project_id": "11dc9a2a-bf59-4356-81d4-a5fd5fe6e9a0",
      "project_code": "OBR-2025-005",
      "project_name": "Collado de Marichiva 5",
      "issue_date": "2025-10-09",
      "amount_total": 13461.6,
      "created_at": "2026-05-09T20:35:19.651872+00:00"
    },
    {
      "id": "909a3a20-f305-4add-bcc5-004358f6eddb",
      "number": "F250019",
      "file_hash": "477b917610b91f3895b8db9c070c860923de6c0970f00dffb66d07efc2a275ce",
      "email_message_id": "batch7-1-1778358805",
      "original_filename": "176xbzmV1y6BCtXkC0_rosJL8hGm7rDf-__ajc_cousillas_F250019_CATHEDRAL_HOUSE_INVESTMENT_SL.pdf",
      "direction": "recibida",
      "doc_type": "factura",
      "review_status": "error",
      "payment_status": "pendiente",
      "supplier_id": "fea68f88-7d37-45f8-8428-53497dc53a2d",
      "supplier_nif": "B72946395",
      "supplier_name": "ACJ Cousillas S.L.",
      "project_id": "f739756c-86f4-472a-9313-1ccb1915f34f",
      "project_code": "OBR-2025-004",
      "project_name": "Majadahonda",
      "issue_date": "2025-03-30",
      "amount_total": 7260,
      "created_at": "2026-05-09T20:33:42.934283+00:00"
    },
    {
      "id": "de81fc25-0573-4ba8-b440-6916072c745e",
      "number": "CHI 05-25",
      "file_hash": "728214c19fa2358228b2d76c7c0df48d62edd19601fcf18dfbd3a634f4bf9046",
      "email_message_id": "cascada-fresh-majadahonda-1778356927",
      "original_filename": "CHI_05-25_MAJADAHONDA.pdf",
      "direction": "emitida",
      "doc_type": "factura",
      "review_status": "pendiente",
      "payment_status": "pendiente",
      "supplier_id": null,
      "supplier_nif": null,
      "supplier_name": null,
      "project_id": "f739756c-86f4-472a-9313-1ccb1915f34f",
      "project_code": "OBR-2025-004",
      "project_name": "Majadahonda",
      "issue_date": "2025-05-06",
      "amount_total": 11573.18,
      "created_at": "2026-05-09T20:02:43.840513+00:00"
    },
    {
      "id": "2ef7f546-575b-4e6d-aec6-2cc8745f7c8c",
      "number": "CHI 007-25",
      "file_hash": "00ba041ca10273e25a659db33fa2f19e1c27c03140a4f1154d875ca1bb72c6b0",
      "email_message_id": "cascada-marichiva5-dpi300-1778354809",
      "original_filename": "CHI_007-25_MARICHIVA_5.pdf",
      "direction": "emitida",
      "doc_type": "factura",
      "review_status": "pendiente",
      "payment_status": "pendiente",
      "supplier_id": null,
      "supplier_nif": null,
      "supplier_name": null,
      "project_id": "11dc9a2a-bf59-4356-81d4-a5fd5fe6e9a0",
      "project_code": "OBR-2025-005",
      "project_name": "Collado de Marichiva 5",
      "issue_date": "2025-07-15",
      "amount_total": 26840,
      "created_at": "2026-05-09T19:56:34.303414+00:00"
    },
    {
      "id": "c3732f6a-f34f-4ce7-84fb-1edb1cca3a36",
      "number": "311100267014",
      "file_hash": "cc1173e0f34db3e6f251f396ec3135a88302f521780d2433cef8c9a7d1b6c9e6",
      "email_message_id": "19de37ca8040f243",
      "original_filename": "Factura_2026-05-01_311100267014_V102512933.pdf",
      "direction": "recibida",
      "doc_type": "factura",
      "review_status": "pendiente",
      "payment_status": "pendiente",
      "supplier_id": "fec83989-925e-482e-848b-b0c42199779a",
      "supplier_nif": "B85049435",
      "supplier_name": "IONOS Cloud S.L.U.",
      "project_id": null,
      "project_code": null,
      "project_name": null,
      "issue_date": "2026-05-01",
      "amount_total": null,
      "created_at": "2026-05-01T13:47:45.162549+00:00"
    },
    {
      "id": "6ffcc7cd-f205-415f-8d4d-8ee1adad3a76",
      "number": "26058",
      "file_hash": "5b7c518c7ecb0903ab95c2d498dc08c948bb65c74fb6ddec44dd27b78552cccd",
      "email_message_id": "19dc6e0346f994a3",
      "original_filename": "CATHEDRAL. FINAL PUERTO RICO.pdf",
      "direction": "recibida",
      "doc_type": "factura",
      "review_status": "pendiente",
      "payment_status": "pendiente",
      "supplier_id": "ea925b1d-5dce-4e51-9065-75883b9d5638",
      "supplier_nif": "B78025426",
      "supplier_name": "Muebles de Cocina Aries",
      "project_id": null,
      "project_code": null,
      "project_name": null,
      "issue_date": "2026-04-23",
      "amount_total": 3169.68,
      "created_at": "2026-04-26T16:37:15.687381+00:00"
    },
    {
      "id": "c2d84b06-0cfe-408e-890b-cf49ae02309e",
      "number": "016-0004-072630",
      "file_hash": "fa315dfdb9cafd6ae431fe43fd6ce32666e6234a2e8fe7dfa1deea03d86b1176",
      "email_message_id": "19d873bf1d20f9c7",
      "original_filename": "b3d5cfdd-9f3e-4e0c-844f-a0a6d4148eda.pdf",
      "direction": "recibida",
      "doc_type": "factura",
      "review_status": "pendiente",
      "payment_status": "pendiente",
      "supplier_id": "2f8fd5ef-7174-412d-91c0-364ac45120f2",
      "supplier_nif": "B84818442",
      "supplier_name": "Leroy Merlin Espana S.L.U.",
      "project_id": null,
      "project_code": null,
      "project_name": null,
      "issue_date": "2026-04-13",
      "amount_total": 72.77,
      "created_at": "2026-04-13T17:33:52.844208+00:00"
    },
    {
      "id": "8efc3493-c962-4ec1-ac5c-dec652e25532",
      "number": "3726",
      "file_hash": "06b55b21951440d59183c7157576b2afe4737cecae3bfcea80a3ba769047ad12",
      "email_message_id": "19d858e4ed50f016",
      "original_filename": "FACTURA 3726 CCC.pdf",
      "direction": "recibida",
      "doc_type": "factura",
      "review_status": "pendiente",
      "payment_status": "pendiente",
      "supplier_id": null,
      "supplier_nif": "B19761915",
      "supplier_name": null,
      "project_id": null,
      "project_code": null,
      "project_name": null,
      "issue_date": "2026-04-13",
      "amount_total": 506.99,
      "created_at": "2026-04-13T17:28:22.92457+00:00"
    },
    {
      "id": "d327df34-d2aa-4d66-8daa-e52e9700cd54",
      "number": "A8425",
      "file_hash": "75d788e98cfacec6b86995e6e4d5d958af270f89c7a0f7d4d9d4bd2f8e557338",
      "email_message_id": "19d54ffefd99b513",
      "original_filename": "AlpanuCN_8425.pdf",
      "direction": "recibida",
      "doc_type": "factura",
      "review_status": "revisado",
      "payment_status": "pendiente",
      "supplier_id": "f1e7fa91-5d2a-481b-9242-8638521ad641",
      "supplier_nif": "B-84074293",
      "supplier_name": "Alpanu CN S.L.",
      "project_id": null,
      "project_code": null,
      "project_name": null,
      "issue_date": "2026-04-01",
      "amount_total": 48.56,
      "created_at": "2026-04-04T17:59:00.650971+00:00"
    },
    {
      "id": "eaa15715-c0f3-4979-b5ca-ae7f2eb97bed",
      "number": "202786025216",
      "file_hash": "7575777396741178413a33dec384bf42f613a080cd4c47eb26f917ae851c2373",
      "email_message_id": "19d4f735b7abffed",
      "original_filename": "Factura_2026-04-02_202786025216_V102512933.pdf",
      "direction": "recibida",
      "doc_type": "factura",
      "review_status": "revisado",
      "payment_status": "pendiente",
      "supplier_id": "fec83989-925e-482e-848b-b0c42199779a",
      "supplier_nif": "B85049435",
      "supplier_name": "IONOS Cloud S.L.U.",
      "project_id": null,
      "project_code": null,
      "project_name": null,
      "issue_date": "2026-04-02",
      "amount_total": 19.36,
      "created_at": "2026-04-04T08:38:53.334446+00:00"
    },
    {
      "id": "1d56f4dd-28bc-4efb-a619-8b8d0fa152bf",
      "number": "ES500FPJ005H7I",
      "file_hash": "a6c222fe6436462bcfd1de7b1ccac36a08cb597df2a29cd41971911bb4c33b6e",
      "email_message_id": null,
      "original_filename": "09.30.2025 _ CT Global (UK) LTD - ESN6060644I _ ES500FPJ005H7I _ 22.45 - 0.00 - 0 _removed.pdf",
      "direction": "recibida",
      "doc_type": "factura",
      "review_status": "revisado",
      "payment_status": "pagada",
      "supplier_id": null,
      "supplier_nif": "ESN6060644I",
      "supplier_name": null,
      "project_id": null,
      "project_code": null,
      "project_name": null,
      "issue_date": "2025-09-30",
      "amount_total": 22.45,
      "created_at": "2026-04-01T23:12:15.776574+00:00"
    },
    {
      "id": "a6baa65c-9d99-4cb4-b019-cbc0ecd8c941",
      "number": "GB50000710Y4JI",
      "file_hash": "febba0ca3e3a7e2a6887907f2eb745cede99507f9e51cc06fb427df765539f23",
      "email_message_id": null,
      "original_filename": "factura espejo c juan cortes 6.pdf",
      "direction": "recibida",
      "doc_type": "factura",
      "review_status": "revisado",
      "payment_status": "pagada",
      "supplier_id": null,
      "supplier_nif": "GB439 0880 73",
      "supplier_name": null,
      "project_id": null,
      "project_code": null,
      "project_name": null,
      "issue_date": "2025-04-20",
      "amount_total": 192.79,
      "created_at": "2026-04-01T23:12:15.775247+00:00"
    },
    {
      "id": "10ba3bb3-417d-4889-a142-203db3c95118",
      "number": "9448593337",
      "file_hash": "4f46f07a7cabedd809ab9648157df43ecf520c294113bbad493c51310a5b3e53",
      "email_message_id": null,
      "original_filename": "Eurocaja Rural6.pdf",
      "direction": "recibida",
      "doc_type": "otro",
      "review_status": "revisado",
      "payment_status": "pagada",
      "supplier_id": null,
      "supplier_nif": "ES42000E78196912",
      "supplier_name": null,
      "project_id": null,
      "project_code": null,
      "project_name": null,
      "issue_date": "2025-12-01",
      "amount_total": 52.83,
      "created_at": "2026-04-01T23:12:15.771479+00:00"
    },
    {
      "id": "b363719d-0048-4fc8-8be8-8491721b71ae",
      "number": "RPOMVP202500050644",
      "file_hash": "f6774c512c5c0476df118d9e3c86c976f940bbe56afd3d79a137b05e4383cd9e",
      "email_message_id": null,
      "original_filename": "290498993.pdf",
      "direction": "recibida",
      "doc_type": "otro",
      "review_status": "revisado",
      "payment_status": "pendiente",
      "supplier_id": null,
      "supplier_nif": null,
      "supplier_name": null,
      "project_id": null,
      "project_code": null,
      "project_name": null,
      "issue_date": "2025-11-12",
      "amount_total": 279.36,
      "created_at": "2026-04-01T23:12:15.758415+00:00"
    },
    {
      "id": "c8728140-6597-468b-b88b-b611d3a62b27",
      "number": "CHI 06-25",
      "file_hash": "5cc0f1f5e23c6996962f4df242860e8c6cd0d8a6e895285a39207fd476f2854a",
      "email_message_id": null,
      "original_filename": "CHI 06-25 2ª  FINAL REFORMA LIGONDE.pdf",
      "direction": "emitida",
      "doc_type": "factura",
      "review_status": "revisado",
      "payment_status": "pendiente",
      "supplier_id": null,
      "supplier_nif": "B-19761915",
      "supplier_name": null,
      "project_id": null,
      "project_code": null,
      "project_name": null,
      "issue_date": "2025-05-16",
      "amount_total": 1230.57,
      "created_at": "2026-04-01T23:12:15.745582+00:00"
    },
    {
      "id": "e9468e98-071d-4b91-80c7-6a54b14ac6c5",
      "number": "VP2025269",
      "file_hash": "295549ca72a5a85ca14fd4c07ad6c5e0f50bf217b6935e72a9a7bb6b38d09b52",
      "email_message_id": null,
      "original_filename": "VP2025269 CATHEDRAL HOUSE INVEST. CL.HERNAN CORTES 6 (100%).pdf",
      "direction": "emitida",
      "doc_type": "factura",
      "review_status": "revisado",
      "payment_status": "pendiente",
      "supplier_id": null,
      "supplier_nif": "B45797297",
      "supplier_name": null,
      "project_id": null,
      "project_code": null,
      "project_name": null,
      "issue_date": "2025-04-30",
      "amount_total": 3746.58,
      "created_at": "2026-04-01T23:12:15.734138+00:00"
    },
    {
      "id": "77af59da-cf9e-4199-840a-5631f1191b8d",
      "number": "9447535357",
      "file_hash": "fa0c16e71f32076fa174d52fdd29a804ff195f99864d033a3e5c33e8608abde2",
      "email_message_id": null,
      "original_filename": "Eurocaja Rural2.pdf",
      "direction": "recibida",
      "doc_type": "otro",
      "review_status": "revisado",
      "payment_status": "pagada",
      "supplier_id": null,
      "supplier_nif": null,
      "supplier_name": null,
      "project_id": null,
      "project_code": null,
      "project_name": null,
      "issue_date": "2025-11-04",
      "amount_total": 52.96,
      "created_at": "2026-04-01T23:12:15.723837+00:00"
    },
    {
      "id": "4c2f9f5e-2a5b-4cc6-bec9-9cb0e370f7ed",
      "number": "25/046",
      "file_hash": "0d4acd3df126052f8111105aedd9f1f0696d7a56745febf74decf8a086b93499",
      "email_message_id": null,
      "original_filename": "Fra. C - Hernan Cortes, 9 - Majadahonda-.pdf",
      "direction": "recibida",
      "doc_type": "factura",
      "review_status": "revisado",
      "payment_status": "pendiente",
      "supplier_id": "6cd2bc22-e3f7-4c70-815a-c7a0565e78dd",
      "supplier_nif": "B87399788",
      "supplier_name": "Hidroparquet",
      "project_id": null,
      "project_code": null,
      "project_name": null,
      "issue_date": "2025-04-21",
      "amount_total": 2220.35,
      "created_at": "2026-04-01T23:12:15.723687+00:00"
    },
    {
      "id": "7164a365-d5e2-45c2-a543-d22be6cf3ecf",
      "number": "9448731790",
      "file_hash": "4a8ce09d49fca7651a5ffe307cf84365e49a8f9e3056c51cae3799bf800511f4",
      "email_message_id": null,
      "original_filename": "Eurocaja Rural4.pdf",
      "direction": "recibida",
      "doc_type": "otro",
      "review_status": "revisado",
      "payment_status": "pagada",
      "supplier_id": null,
      "supplier_nif": null,
      "supplier_name": null,
      "project_id": null,
      "project_code": null,
      "project_name": null,
      "issue_date": "2025-12-03",
      "amount_total": 29.55,
      "created_at": "2026-04-01T23:12:15.708922+00:00"
    },
    {
      "id": "dd32ecda-dbd7-4791-a40a-946d87f4601b",
      "number": "ES5000AIA5OUNI",
      "file_hash": "d4e5ef9a234c23337c00eda0827a77ea59e65727c2168dff6e02da1d58d50edb",
      "email_message_id": null,
      "original_filename": "09.22.2025 _ Nediventa Online S.L - B88402128 _ ES5000AIA5OUNI _ 302.32 - 63.49 - 21 %.pdf",
      "direction": "recibida",
      "doc_type": "factura",
      "review_status": "revisado",
      "payment_status": "pagada",
      "supplier_id": null,
      "supplier_nif": "ESB88402128",
      "supplier_name": null,
      "project_id": null,
      "project_code": null,
      "project_name": null,
      "issue_date": "2025-09-22",
      "amount_total": 365.81,
      "created_at": "2026-04-01T23:12:15.700506+00:00"
    },
    {
      "id": "e3123c89-1baf-4572-92a5-24ea0e4b225e",
      "number": null,
      "file_hash": "7ea1e0caa092a885b500126f96822a6e6f9b1add6565634ed4ce62ad16292768",
      "email_message_id": null,
      "original_filename": "281301844.pdf",
      "direction": "recibida",
      "doc_type": "otro",
      "review_status": "revisado",
      "payment_status": "pendiente",
      "supplier_id": null,
      "supplier_nif": "F-45003993",
      "supplier_name": null,
      "project_id": null,
      "project_code": null,
      "project_name": null,
      "issue_date": "2025-09-01",
      "amount_total": 253.5,
      "created_at": "2026-04-01T23:12:15.695057+00:00"
    },
    {
      "id": "d25fa21c-fccb-48f9-a761-30049059eb3e",
      "number": "B2010125-00008093",
      "file_hash": "4d651b59e7b263e431d893262fe78ad12cd90ed8a7788b966565e1183eb0e6c4",
      "email_message_id": null,
      "original_filename": "C2672B50-C551-433D-83E5-875975D8C715.pdf",
      "direction": "recibida",
      "doc_type": "factura",
      "review_status": "revisado",
      "payment_status": "pagada",
      "supplier_id": "76cb0bb5-ec39-43d1-bc26-91d3132e1795",
      "supplier_nif": "B85057974",
      "supplier_name": "Orange Espana Virtual S.L.U. (Simyo)",
      "project_id": null,
      "project_code": null,
      "project_name": null,
      "issue_date": "2025-02-07",
      "amount_total": 15,
      "created_at": "2026-04-01T23:12:15.688617+00:00"
    },
    {
      "id": "38ac271d-e9ba-4b04-a631-83086c33a12c",
      "number": "ES5000SOEQR4DC",
      "file_hash": "c9386b3cc8983381a240a9643c3a796a5cbfd8f658f9221cb5ad9a54aa02675a",
      "email_message_id": null,
      "original_filename": "10.07.2025 _ Jabiru Web S.L - B40560963 _ ES5000SOEQR4DC _ -179.34 - -37.66 - 21 %.pdf",
      "direction": "recibida",
      "doc_type": "rectificativa",
      "review_status": "revisado",
      "payment_status": "pendiente",
      "supplier_id": null,
      "supplier_nif": "ESB40560963",
      "supplier_name": null,
      "project_id": null,
      "project_code": null,
      "project_name": null,
      "issue_date": "2025-10-07",
      "amount_total": -217,
      "created_at": "2026-04-01T23:12:15.683548+00:00"
    },
    {
      "id": "cae57eca-7d60-40c7-a83d-7b5b5bddcbc0",
      "number": null,
      "file_hash": "73999685cc7135531763d44770c7360782be5a414e51dee454a4a7580fbad6d8",
      "email_message_id": null,
      "original_filename": "291812691.pdf",
      "direction": "recibida",
      "doc_type": "otro",
      "review_status": "revisado",
      "payment_status": "pendiente",
      "supplier_id": null,
      "supplier_nif": "F-45003993",
      "supplier_name": null,
      "project_id": null,
      "project_code": null,
      "project_name": null,
      "issue_date": "2025-12-01",
      "amount_total": 139.1,
      "created_at": "2026-04-01T23:12:15.679166+00:00"
    },
    {
      "id": "1398de4b-7573-4fad-a16b-cf61ae59911a",
      "number": "9449044591",
      "file_hash": "7f48ddcc8dbca5340232de3512b3130609eb93c67520e10f2fb8f50aa9b488ff",
      "email_message_id": null,
      "original_filename": "Eurocaja Rural5.pdf",
      "direction": "recibida",
      "doc_type": "otro",
      "review_status": "revisado",
      "payment_status": "pagada",
      "supplier_id": null,
      "supplier_nif": null,
      "supplier_name": null,
      "project_id": null,
      "project_code": null,
      "project_name": null,
      "issue_date": "2025-12-10",
      "amount_total": 80.37,
      "created_at": "2026-04-01T23:12:15.673601+00:00"
    },
    {
      "id": "e3006eca-3e20-4ced-ac09-6b4766c50f52",
      "number": "RPOMVP202500053087",
      "file_hash": "9b351b4796791ed65b054332e89aaf87881a9a8d7b87aa51bcf42429ce4c28c7",
      "email_message_id": null,
      "original_filename": "290956797.pdf",
      "direction": "recibida",
      "doc_type": "otro",
      "review_status": "revisado",
      "payment_status": "pendiente",
      "supplier_id": null,
      "supplier_nif": null,
      "supplier_name": null,
      "project_id": null,
      "project_code": null,
      "project_name": null,
      "issue_date": "2025-11-24",
      "amount_total": 60.39,
      "created_at": "2026-04-01T23:12:15.67325+00:00"
    },
    {
      "id": "85587fa2-a893-4051-a9c2-64ffa480234d",
      "number": "2514625709",
      "file_hash": "78752173b4e626c2bc79f5d636144ec34b560f5ad48dfcbcf50395ce2c0eea09",
      "email_message_id": null,
      "original_filename": "290229768.pdf",
      "direction": "recibida",
      "doc_type": "otro",
      "review_status": "revisado",
      "payment_status": "pendiente",
      "supplier_id": null,
      "supplier_nif": "B19761915",
      "supplier_name": null,
      "project_id": null,
      "project_code": null,
      "project_name": null,
      "issue_date": "2025-11-13",
      "amount_total": 51.35,
      "created_at": "2026-04-01T23:12:15.665123+00:00"
    },
    {
      "id": "a51061e8-207a-4e36-b880-a93c54de1c09",
      "number": "9447981347",
      "file_hash": "aa1667c1b8195dc6ae9d5950ce66362f73e1cf9fa6d6865f41d806e2e1cb33ce",
      "email_message_id": null,
      "original_filename": "290684853.pdf",
      "direction": "recibida",
      "doc_type": "otro",
      "review_status": "revisado",
      "payment_status": "pendiente",
      "supplier_id": null,
      "supplier_nif": "ES72111A28534345",
      "supplier_name": null,
      "project_id": null,
      "project_code": null,
      "project_name": null,
      "issue_date": "2025-11-19",
      "amount_total": 45.32,
      "created_at": "2026-04-01T23:12:15.656462+00:00"
    },
    {
      "id": "b3a789c2-5c90-494f-b3e9-f76ae4a90781",
      "number": "RPOMVP202500051378",
      "file_hash": "3874e1ef72d16175f78ed47923383690abe8b8fa3b347b6c9ca5a998bcf3cef2",
      "email_message_id": null,
      "original_filename": "290684631.pdf",
      "direction": "recibida",
      "doc_type": "otro",
      "review_status": "revisado",
      "payment_status": "pendiente",
      "supplier_id": null,
      "supplier_nif": "ES72111A28534345",
      "supplier_name": null,
      "project_id": null,
      "project_code": null,
      "project_name": null,
      "issue_date": "2025-11-19",
      "amount_total": 79.78,
      "created_at": "2026-04-01T23:12:15.650838+00:00"
    },
    {
      "id": "ff8ef804-83aa-4a0c-8fc9-b5e78f837af9",
      "number": "RPOMVP202500050646",
      "file_hash": "2608eff6c9cecba62f19df4f6f6476ac3ab1aa4ec2719a656b48ce01ed2e6239",
      "email_message_id": null,
      "original_filename": "290499025.pdf",
      "direction": "recibida",
      "doc_type": "otro",
      "review_status": "revisado",
      "payment_status": "pendiente",
      "supplier_id": null,
      "supplier_nif": null,
      "supplier_name": null,
      "project_id": null,
      "project_code": null,
      "project_name": null,
      "issue_date": "2025-11-12",
      "amount_total": 188.09,
      "created_at": "2026-04-01T23:12:15.636828+00:00"
    },
    {
      "id": "d14fe333-0608-455f-901a-783ecda8e01a",
      "number": "007-0010-274317",
      "file_hash": "6b6bc5b96ed684eb078569c9c28de17d6020dd00e0d7fd44c77126fed5f97e86",
      "email_message_id": null,
      "original_filename": "10.08.2025 _ OBRAMAT BRICOLAJE BRICOMAN SLU - B84406289 _ 007-0010-274317 _ 1.296,17 - 272,20 .pdf",
      "direction": "recibida",
      "doc_type": "factura",
      "review_status": "revisado",
      "payment_status": "pagada",
      "supplier_id": "8af9ef38-7e71-49e7-831a-20105094319e",
      "supplier_nif": "B-84406289",
      "supplier_name": "Obramat / Bricoman S.L.U.",
      "project_id": null,
      "project_code": null,
      "project_name": null,
      "issue_date": "2025-10-08",
      "amount_total": 1568.37,
      "created_at": "2026-04-01T23:12:15.629347+00:00"
    },
    {
      "id": "cb51865c-27e6-4e9c-b6ba-96ee275fed7e",
      "number": "RPOMVP202500017913",
      "file_hash": "1a632f193440deea5a14d612965bb1b4c74c10e0f19de84e737f9d94c6c1cce3",
      "email_message_id": null,
      "original_filename": "280589845.pdf",
      "direction": "recibida",
      "doc_type": "otro",
      "review_status": "revisado",
      "payment_status": "pendiente",
      "supplier_id": null,
      "supplier_nif": "ES72111A28534345",
      "supplier_name": null,
      "project_id": null,
      "project_code": null,
      "project_name": null,
      "issue_date": "2025-08-14",
      "amount_total": 45.85,
      "created_at": "2026-04-01T23:12:15.62304+00:00"
    },
    {
      "id": "f4af8e1b-f28e-4893-b5c5-a5ccd5d5682e",
      "number": "9444234943",
      "file_hash": "836ab8d56b18d7b059b87d74870a2ce713c92188c8521b748cd7379f20a761a2",
      "email_message_id": null,
      "original_filename": "280656270.pdf",
      "direction": "recibida",
      "doc_type": "otro",
      "review_status": "revisado",
      "payment_status": "pendiente",
      "supplier_id": null,
      "supplier_nif": "ES72111A28534345",
      "supplier_name": null,
      "project_id": null,
      "project_code": null,
      "project_name": null,
      "issue_date": "2025-08-14",
      "amount_total": 80.24,
      "created_at": "2026-04-01T23:12:15.618709+00:00"
    }
  ]
}